loca/__init__.py
loca/macos.py
loca/py.typed
loca/windows.py
loca/xdg.py
loca-2.0.1.dist-info/COPYING
loca-2.0.1.dist-info/WHEEL
loca-2.0.1.dist-info/METADATA
loca-2.0.1.dist-info/RECORD
